{
  "formatVersion": 1,
  "database": {
    "version": 4,
    "identityHash": "8653fdb8b36b1413cabfaf71b47d4145",
    "entities": [
      {
        "tableName": "tbl_screen",
        "createSql": "CREATE TABLE IF NOT EXISTS `${TABLE_NAME}` (`id` INTEGER PRIMARY KEY AUTOINCREMENT NOT NULL, `screenId` TEXT NOT NULL, `dispatcherCode` INTEGER NOT NULL, `marginTop` INTEGER NOT NULL, `marginBottom` INTEGER NOT NULL, `marginLeft` INTEGER NOT NULL, `marginRight` INTEGER NOT NULL, `elements` TEXT NOT NULL)",
        "fields": [
          {
            "fieldPath": "id",
            "columnName": "id",
            "affinity": "INTEGER",
            "notNull": true
          },
          {
            "fieldPath": "screenId",
            "columnName": "screenId",
            "affinity": "TEXT",
            "notNull": true
          },
          {
            "fieldPath": "dispatcherCode",
            "columnName": "dispatcherCode",
            "affinity": "INTEGER",
            "notNull": true
          },
          {
            "fieldPath": "marginTop",
            "columnName": "marginTop",
            "affinity": "INTEGER",
            "notNull": true
          },
          {
            "fieldPath": "marginBottom",
            "columnName": "marginBottom",
            "affinity": "INTEGER",
            "notNull": true
          },
          {
            "fieldPath": "marginLeft",
            "columnName": "marginLeft",
            "affinity": "INTEGER",
            "notNull": true
          },
          {
            "fieldPath": "marginRight",
            "columnName": "marginRight",
            "affinity": "INTEGER",
            "notNull": true
          },
          {
            "fieldPath": "elements",
            "columnName": "elements",
            "affinity": "TEXT",
            "notNull": true
          }
        ],
        "primaryKey": {
          "autoGenerate": true,
          "columnNames": [
            "id"
          ]
        },
        "indices": [],
        "foreignKeys": []
      },
      {
        "tableName": "tbl_dashboard_device",
        "createSql": "CREATE TABLE IF NOT EXISTS `${TABLE_NAME}` (`id` INTEGER PRIMARY KEY AUTOINCREMENT NOT NULL, `deviceIp` TEXT NOT NULL, `customName` TEXT NOT NULL, `terminalIp` TEXT)",
        "fields": [
          {
            "fieldPath": "id",
            "columnName": "id",
            "affinity": "INTEGER",
            "notNull": true
          },
          {
            "fieldPath": "deviceIp",
            "columnName": "deviceIp",
            "affinity": "TEXT",
            "notNull": true
          },
          {
            "fieldPath": "customName",
            "columnName": "customName",
            "affinity": "TEXT",
            "notNull": true
          },
          {
            "fieldPath": "terminalIp",
            "columnName": "terminalIp",
            "affinity": "TEXT",
            "notNull": false
          }
        ],
        "primaryKey": {
          "autoGenerate": true,
          "columnNames": [
            "id"
          ]
        },
        "indices": [],
        "foreignKeys": []
      },
      {
        "tableName": "tbl_images",
        "createSql": "CREATE TABLE IF NOT EXISTS `${TABLE_NAME}` (`id` INTEGER PRIMARY KEY AUTOINCREMENT NOT NULL, `fileName` TEXT, `fileContent` TEXT)",
        "fields": [
          {
            "fieldPath": "id",
            "columnName": "id",
            "affinity": "INTEGER",
            "notNull": true
          },
          {
            "fieldPath": "fileName",
            "columnName": "fileName",
            "affinity": "TEXT",
            "notNull": false
          },
          {
            "fieldPath": "fileContent",
            "columnName": "fileContent",
            "affinity": "TEXT",
            "notNull": false
          }
        ],
        "primaryKey": {
          "autoGenerate": true,
          "columnNames": [
            "id"
          ]
        },
        "indices": [],
        "foreignKeys": []
      }
    ],
    "views": [],
    "setupQueries": [
      "CREATE TABLE IF NOT EXISTS room_master_table (id INTEGER PRIMARY KEY,identity_hash TEXT)",
      "INSERT OR REPLACE INTO room_master_table (id,identity_hash) VALUES(42, '8653fdb8b36b1413cabfaf71b47d4145')"
    ]
  }
}